CompressDataFrame/CompressDataFrame.py
CompressDataFrame/__init__.py
compress-dataframe/__init__.py
compress-dataframe/compress-df.py
CompressDataFrame-0.0.2.dist-info/LICENSE
CompressDataFrame-0.0.2.dist-info/METADATA
CompressDataFrame-0.0.2.dist-info/WHEEL
CompressDataFrame-0.0.2.dist-info/top_level.txt
CompressDataFrame-0.0.2.dist-info/RECORD
